{
 "charts": [],
 "content": "[{\"id\":\"z4UEc2FgRr\",\"type\":\"header\",\"data\":{\"text\":\"<span class=\\\"h4\\\">Meher</span>\",\"col\":12}},{\"id\":\"AzbDpVDyil\",\"type\":\"card\",\"data\":{\"card_name\":\"Masters\",\"col\":4}},{\"id\":\"iKL1XOA3K7\",\"type\":\"card\",\"data\":{\"card_name\":\"Reports\",\"col\":4}}]",
 "creation": "2026-02-19 06:41:25.360732",
 "custom_blocks": [],
 "docstatus": 0,
 "doctype": "Workspace",
 "for_user": "",
 "hide_custom": 0,
 "icon": "education",
 "idx": 0,
 "indicator_color": "green",
 "is_hidden": 0,
 "label": "Meher",
 "links": [
  {
   "hidden": 0,
   "is_query_report": 0,
   "label": "Masters",
   "link_count": 5,
   "link_type": "DocType",
   "onboard": 0,
   "type": "Card Break"
  },
  {
   "hidden": 0,
   "is_query_report": 0,
   "label": "Container",
   "link_count": 0,
   "link_to": "Container",
   "link_type": "DocType",
   "onboard": 0,
   "type": "Link"
  },
  {
   "hidden": 0,
   "is_query_report": 0,
   "label": "Print Batch",
   "link_count": 0,
   "link_to": "Print Batch",
   "link_type": "DocType",
   "onboard": 0,
   "type": "Link"
  },
  {
   "hidden": 0,
   "is_query_report": 0,
   "label": "Batch",
   "link_count": 0,
   "link_to": "Batch",
   "link_type": "DocType",
   "onboard": 0,
   "type": "Link"
  },
  {
   "hidden": 0,
   "is_query_report": 0,
   "label": "Delivery Note",
   "link_count": 0,
   "link_to": "Delivery Note",
   "link_type": "DocType",
   "onboard": 0,
   "type": "Link"
  },
  {
   "hidden": 0,
   "is_query_report": 0,
   "label": "Purchase Receipt",
   "link_count": 0,
   "link_to": "Purchase Receipt",
   "link_type": "DocType",
   "onboard": 0,
   "type": "Link"
  },
  {
   "hidden": 0,
   "is_query_report": 0,
   "label": "Reports",
   "link_count": 6,
   "link_type": "DocType",
   "onboard": 0,
   "type": "Card Break"
  },
  {
   "hidden": 0,
   "is_query_report": 1,
   "label": "Container Report",
   "link_count": 0,
   "link_to": "Container Report",
   "link_type": "Report",
   "onboard": 0,
   "type": "Link"
  },
  {
   "hidden": 0,
   "is_query_report": 1,
   "label": "DELIVERY CHALLAN",
   "link_count": 0,
   "link_to": "DELIVERY CHALLAN",
   "link_type": "Report",
   "onboard": 0,
   "type": "Link"
  },
  {
   "hidden": 0,
   "is_query_report": 1,
   "label": "STOCK SHEET (BALANCE REPORT)",
   "link_count": 0,
   "link_to": "STOCK SHEET (BALANCE REPORT)",
   "link_type": "Report",
   "onboard": 0,
   "type": "Link"
  },
  {
   "hidden": 0,
   "is_query_report": 1,
   "label": "STOCK SHEET (INWARD CONE WISE)",
   "link_count": 0,
   "link_to": "STOCK SHEET (INWARD CONE WISE)",
   "link_type": "Report",
   "onboard": 0,
   "type": "Link"
  },
  {
   "hidden": 0,
   "is_query_report": 1,
   "label": "STOCK SHEETS (INWARD CONELESS STOCK )",
   "link_count": 0,
   "link_to": "STOCK SHEETS (INWARD CONELESS STOCK )",
   "link_type": "Report",
   "onboard": 0,
   "type": "Link"
  },
  {
   "hidden": 0,
   "is_query_report": 1,
   "label": "STOCK SHEETS (INWARD REST STOCK )",
   "link_count": 0,
   "link_to": "STOCK SHEETS (INWARD REST STOCK )",
   "link_type": "Report",
   "onboard": 0,
   "type": "Link"
  }
 ],
 "modified": "2026-02-19 06:51:15.834591",
 "modified_by": "Administrator",
 "module": "Mhr",
 "name": "Meher",
 "number_cards": [],
 "owner": "Administrator",
 "parent_page": "",
 "public": 1,
 "quick_lists": [],
 "roles": [],
 "sequence_id": 39.0,
 "shortcuts": [],
 "title": "Meher"
}